sarge/__init__.py
sarge/shlext.py
sarge/utils.py
sarge-0.1.8.dist-info/LICENSE
sarge-0.1.8.dist-info/METADATA
sarge-0.1.8.dist-info/WHEEL
sarge-0.1.8.dist-info/top_level.txt
sarge-0.1.8.dist-info/RECORD
